src/core.py
text2heximage/__init__.py
text2heximage/core.py
Text2HexImage-1.0.2.dist-info/LICENSE
Text2HexImage-1.0.2.dist-info/METADATA
Text2HexImage-1.0.2.dist-info/WHEEL
Text2HexImage-1.0.2.dist-info/top_level.txt
Text2HexImage-1.0.2.dist-info/RECORD
