Metadata-Version: 2.1
Name: Text2HexImage
Version: 1.0.2
Summary: Text to Hex Image
Home-page: https://github.com/Team-DeVent/text2heximage
Author: Team-DeVent
Author-email: hhj@devent.kr
License: MIT
Platform: UNKNOWN
Requires-Python: >=3
